quadrantrecon-1.1.0.dist-info/METADATA
quadrantrecon-1.1.0.dist-info/WHEEL
quadrantrecon-1.1.0.dist-info/entry_points.txt
quadrantrecon-1.1.0.dist-info/licenses/LICENSE.md
quadrantrecon/__init__.py
quadrantrecon/__main__.py
quadrantrecon/get_image_size.py
quadrantrecon/metadata.py
quadrantrecon/qr.py
quadrantrecon/utils.py
quadrantrecon-1.1.0.dist-info/RECORD
